{
  "data_configuracao": "2025-08-11T14:00:00",
  "cidades": {
    "SC": {
      "8690": "JOINVILLE",
      "8545": "BLUMENAU",
      "8535": "BARRA VELHA",
      "8523": "BALNEARIO BARRA DO SUL",
      "8676": "ITAJAI",
      "8634": "GOVERNADOR CELSO RAMOS"
    },
    "MS": {
      "4198": "CAMPO GRANDE"
    },
    "SP": {
      "9114": "BADY BASSITT"
    },
    "DF": {
      "5300108": "BRASILIA",
      "5300110": "TAGUATINGA",
      "5300111": "CEILANDIA",
      "5300112": "SAMAMBAIA",
      "5300113": "GAMA"
    }
  },
  "observacao": "Códigos atualizados em 2025-08-11. Incluído Distrito Federal (DF) com principais regiões administrativas."
} 